olla/agent/react_agent.py
olla/core/function.py
olla/core/llm.py
olla/core/utils.py
olla/prompt/react.py
olla-0.1.1.dist-info/METADATA
olla-0.1.1.dist-info/WHEEL
olla-0.1.1.dist-info/RECORD
