Metadata-Version: 2.1
Name: olla
Version: 0.1.1
Summary: Open Local LLM Agent
Author: gamersover
Author-email: cmathking@gmail.com
Requires-Python: >=3.9,<4.0
Classifier: Programming Language :: Python :: 3
Classifier: Programming Language :: Python :: 3.9
Classifier: Programming Language :: Python :: 3.10
Classifier: Programming Language :: Python :: 3.11
Classifier: Programming Language :: Python :: 3.12
Requires-Dist: langchain-community (>=0.0.29,<0.0.30)
Requires-Dist: openai (>=1.14.2,<1.15.0)
Requires-Dist: pytz (>=2024.1,<2025.0)
